Metadata-Version: 2.1
Name: mystery
Version: 1.0.1
Summary: It is a riddle, wrapped in a mystery, inside an enigma.
Home-page: https://github.com/DivoK/mystery
Author: Divo Kaplan
Author-email: divokaplan@gmail.com
License: UNKNOWN
Keywords: mystery setuptools fun python-packages random
Platform: UNKNOWN
Classifier: Development Status :: 5 - Production/Stable
Classifier: License :: OSI Approved :: MIT License
Classifier: Operating System :: OS Independent
Classifier: Programming Language :: Python :: 3.6
Classifier: Programming Language :: Python :: 3.7
Classifier: Programming Language :: Python :: 3.8
Classifier: Intended Audience :: Other Audience
Classifier: Topic :: Software Development :: Libraries :: Python Modules
Requires-Python: >=3.6
